{"id":2067,"category_slug":"news","category_name":"News","position":188,"title":"Flying Car Prototype Takes Off","subtitle":"","level":"C1","parts":12,"url":"https://dailydictation.com/exercises/news/flying-car-prototype-takes-off.2067/listen-and-type","audio_url":"","transcript":"Look at this car taking off and hopping over a truck.\nIt's a prototype made by the company Alef Aeronautics,\nwhich hopes to put this 300,000 dollar flying car in the fast lane to reality.\nRight now, for most people (for the general consumer),\nit's prohibitively expensive because it's expensive for us to produce one\nbut it's because it's a very low-volume production and it's very inefficient.\nThis CGI-rendered video shows the automobile flying through the mountains.\nThe FAA said that Alef Aeronautics vehicle is not the first aircraft of its kind to get a special airworthiness certificate.\nHowever, the company notes that its vehicle stands out\nbecause it can drive on roads, fly, and be used in search and rescue.\nModels from companies like SkyDrive, HoverSurf, Volocopter, and others are yet to hit the market\nand make flying cars a reality.","youtube_video_id":"sKFOPR9uRR8","details_cached_at":"2026-06-15T20:55:13","challenges":[{"position":1,"content":"Look at this car taking off and hopping over a truck.","audio_url":"","time_start":462.39,"time_end":465.93},{"position":2,"content":"It's a prototype made by the company Alef Aeronautics,","audio_url":"","time_start":467.07,"time_end":470.31},{"position":3,"content":"which hopes to put this 300,000 dollar flying car in the fast lane to reality.","audio_url":"","time_start":470.19,"time_end":475.11},{"position":4,"content":"Right now, for most people (for the general consumer),","audio_url":"","time_start":476.79,"time_end":480.6},{"position":5,"content":"it's prohibitively expensive because it's expensive for us to produce one","audio_url":"","time_start":480.6,"time_end":484.95},{"position":6,"content":"but it's because it's a very low-volume production and it's very inefficient.","audio_url":"","time_start":485.39,"time_end":491.11},{"position":7,"content":"This CGI-rendered video shows the automobile flying through the mountains.","audio_url":"","time_start":501.05,"time_end":506.19},{"position":8,"content":"The FAA said that Alef Aeronautics vehicle is not the first aircraft of its kind to get a special airworthiness certificate.","audio_url":"","time_start":506.34,"time_end":514.17},{"position":9,"content":"However, the company notes that its vehicle stands out","audio_url":"","time_start":514.42,"time_end":517.39},{"position":10,"content":"because it can drive on roads, fly, and be used in search and rescue.","audio_url":"","time_start":517.39,"time_end":521.92},{"position":11,"content":"Models from companies like SkyDrive, HoverSurf, Volocopter, and others are yet to hit the market","audio_url":"","time_start":522.16,"time_end":528.05},{"position":12,"content":"and make flying cars a reality.","audio_url":"","time_start":528.05,"time_end":530.37}]}