{"id":2290,"category_slug":"medical-english-oet","category_name":"Medical English (OET)","position":24,"title":"Test 03 - Part B - Extract 2","subtitle":"X-ray Department Issues","level":"B2","parts":9,"url":"https://dailydictation.com/exercises/medical-english-oet/test-03-part-b-extract-2.2290/listen-and-type","audio_url":"https://dailydictation.com/upload/medical-english-oet/test-03-part-b-extract-2-2025-08-29-21-58-15/0-test-03-part-b-extract-2.mp3","transcript":"So next on the agenda is the problems in the x-ray department.\nNick, would you like to fill us in here?\nWell, as you all know, this is a very busy department.\nSo we have four x-ray machines in all, including one in the fracture and orthopedic clinic area.\nBut recently, one of the other x-ray machines developed a fault.\nAnd so we had to apply for authorization for the purchase of a new tube for it.\nThere's been some kind of hold up with the paperwork and...\nwhile we've been waiting, patients are being brought into the fracture and orthopedic area for x-rays there instead.\nAnd of course that's causing further congestion.","youtube_video_id":"","details_cached_at":"2026-06-15T20:52:48","challenges":[{"position":1,"content":"So next on the agenda is the problems in the x-ray department.","audio_url":"https://dailydictation.com/upload/medical-english-oet/test-03-part-b-extract-2-2025-08-29-21-58-15/1.mp3","time_start":0.4,"time_end":5.58},{"position":2,"content":"Nick, would you like to fill us in here?","audio_url":"https://dailydictation.com/upload/medical-english-oet/test-03-part-b-extract-2-2025-08-29-21-58-15/2.mp3","time_start":5.58,"time_end":7.8},{"position":3,"content":"Well, as you all know, this is a very busy department.","audio_url":"https://dailydictation.com/upload/medical-english-oet/test-03-part-b-extract-2-2025-08-29-21-58-15/3.mp3","time_start":8.32,"time_end":11.35},{"position":4,"content":"So we have four x-ray machines in all, including one in the fracture and orthopedic clinic area.","audio_url":"https://dailydictation.com/upload/medical-english-oet/test-03-part-b-extract-2-2025-08-29-21-58-15/4.mp3","time_start":11.89,"time_end":17.93},{"position":5,"content":"But recently, one of the other x-ray machines developed a fault.","audio_url":"https://dailydictation.com/upload/medical-english-oet/test-03-part-b-extract-2-2025-08-29-21-58-15/5.mp3","time_start":18.34,"time_end":21.77},{"position":6,"content":"And so we had to apply for authorization for the purchase of a new tube for it.","audio_url":"https://dailydictation.com/upload/medical-english-oet/test-03-part-b-extract-2-2025-08-29-21-58-15/6.mp3","time_start":21.77,"time_end":27.39},{"position":7,"content":"There's been some kind of hold up with the paperwork and...","audio_url":"https://dailydictation.com/upload/medical-english-oet/test-03-part-b-extract-2-2025-08-29-21-58-15/7.mp3","time_start":28.01,"time_end":31.07},{"position":8,"content":"while we've been waiting, patients are being brought into the fracture and orthopedic area for x-rays there instead.","audio_url":"https://dailydictation.com/upload/medical-english-oet/test-03-part-b-extract-2-2025-08-29-21-58-15/8.mp3","time_start":31.07,"time_end":37.63},{"position":9,"content":"And of course that's causing further congestion.","audio_url":"https://dailydictation.com/upload/medical-english-oet/test-03-part-b-extract-2-2025-08-29-21-58-15/9.mp3","time_start":37.73,"time_end":40.65}]}