{"id":566,"category_slug":"ielts-listening","category_name":"IELTS Listening","position":98,"title":"Cam14 - Test 1 - Part 2","subtitle":"Apprenticeship Introduction and Policies","level":"B1","parts":56,"url":"https://dailydictation.com/exercises/ielts-listening/cam14-test-1-part-2.566/listen-and-type","audio_url":"https://dailydictation.com/upload/ielts-listening/ielts-cambridge-14-test-1-section-2-2023-01-25-00-08-54/0-ielts-cambridge-14-test-1-section-2.mp3","transcript":"Good morning everyone.\nMy name's Janet Parker and I'm the human resources manager.\nWe're very happy to welcome you to your new apprenticeship.\nI hope that the next six months will be a positive and enjoyable experience for you.\nI'd like to start with some general advice about being an apprentice.\nMost of you have very little or no experience of working for a big organisation\nand the first week or so may be quite challenging.\nThere will be a lot of new information to take in\nbut don't worry too much about trying to remember everything.\nThe important thing is to check with someone if you're not sure what to do -\nyou'll find your supervisor is very approachable and won't mind explaining things or helping you out.\nYou're here to learn so make the most of that opportunity.\nYou'll be spending time in different departments during your first week\nso make an effort to talk to as many people as possible about their work -\nyou'll make some new friends and find out lots of useful information.\nAs well as having a supervisor, you'll each be assigned a mentor.\nThis person will be someone who's recently completed an apprenticeship\nand you'll meet with them on a weekly basis.\nTheir role is to provide help and support throughout your apprenticeship.\nOf course, this doesn't mean they'll actually do any of your work for you -\ninstead they'll be asking you about what goals you've achieved so far,\nas well as helping you to identify any areas for improvement.\nYou can also discuss your more long-term ambitions with them as well.\nNow I just want to run through a few company policies for our apprenticeship scheme with you...\nMost importantly, the internet.\nAs part of your job you'll be doing some research online\nso obviously you'll have unlimited access for that\nbut please don't use it for personal use,\nyou'll have your own phones for that.\nSome of you have already asked me about flexible working.\nAfter your probationary three-month period,\nsome of you will be eligible for this,\nbut it will depend on which department you're in and what your personal circumstances are.\nSo please don't assume you'll automatically be permitted to do this.\nI want to make sure there's no confusion about our holiday policy.\nApart from any statutory public holidays\nwe ask that you don't book any holidays until after your six-month apprenticeship has finished.\nTime off should only be taken if you are unwell.\nPlease speak to your supervisor if this is going to be a problem.\nYou'll be expected to work a 40-hour week\nbut there may be opportunities to do overtime during busy periods.\nAlthough you're not required to do this,\nit can be a valuable experience -\nso we advise you to take it up if possible.\nObviously, we understand that people do have commitments outside work,\nso don't worry if there are times when you are unavailable.\nAs you know, we don't have a formal dress code here -\nyou may wear casual clothes as long as they're practical -\nand the only restriction for shoes we have is on high heels for health and safety reasons.\nComfortable shoes like trainers are preferable.\nThere's a heavily subsidised canteen on site where you can get hot meals or salads cheaply.\nSnacks and drinks are also provided -\nso we've decided to introduce a no packed lunch policy.\nThis is partly to encourage healthy eating at work\nand partly to stop people from eating at their workstation, which is unhygienic.\nOK moving on to...","youtube_video_id":"","details_cached_at":"2026-06-15T20:50:08","challenges":[{"position":1,"content":"Good morning everyone.","audio_url":"https://dailydictation.com/upload/ielts-listening/ielts-cambridge-14-test-1-section-2-2023-01-25-00-08-54/1.mp3","time_start":0.0,"time_end":2.0},{"position":2,"content":"My name's Janet Parker and I'm the human resources manager.","audio_url":"https://dailydictation.com/upload/ielts-listening/ielts-cambridge-14-test-1-section-2-2023-01-25-00-08-54/2.mp3","time_start":2.15,"time_end":7.17},{"position":3,"content":"We're very happy to welcome you to your new apprenticeship.","audio_url":"https://dailydictation.com/upload/ielts-listening/ielts-cambridge-14-test-1-section-2-2023-01-25-00-08-54/3.mp3","time_start":7.43,"time_end":11.56},{"position":4,"content":"I hope that the next six months will be a positive and enjoyable experience for you.","audio_url":"https://dailydictation.com/upload/ielts-listening/ielts-cambridge-14-test-1-section-2-2023-01-25-00-08-54/4.mp3","time_start":11.81,"time_end":17.71},{"position":5,"content":"I'd like to start with some general advice about being an apprentice.","audio_url":"https://dailydictation.com/upload/ielts-listening/ielts-cambridge-14-test-1-section-2-2023-01-25-00-08-54/5.mp3","time_start":18.12,"time_end":23.2},{"position":6,"content":"Most of you have very little or no experience of working for a big organisation","audio_url":"https://dailydictation.com/upload/ielts-listening/ielts-cambridge-14-test-1-section-2-2023-01-25-00-08-54/6.mp3","time_start":23.6,"time_end":29.61},{"position":7,"content":"and the first week or so may be quite challenging.","audio_url":"https://dailydictation.com/upload/ielts-listening/ielts-cambridge-14-test-1-section-2-2023-01-25-00-08-54/7.mp3","time_start":29.75,"time_end":33.81},{"position":8,"content":"There will be a lot of new information to take in","audio_url":"https://dailydictation.com/upload/ielts-listening/ielts-cambridge-14-test-1-section-2-2023-01-25-00-08-54/8.mp3","time_start":34.05,"time_end":37.03},{"position":9,"content":"but don't worry too much about trying to remember everything.","audio_url":"https://dailydictation.com/upload/ielts-listening/ielts-cambridge-14-test-1-section-2-2023-01-25-00-08-54/9.mp3","time_start":37.2,"time_end":41.88},{"position":10,"content":"The important thing is to check with someone if you're not sure what to do -","audio_url":"https://dailydictation.com/upload/ielts-listening/ielts-cambridge-14-test-1-section-2-2023-01-25-00-08-54/10.mp3","time_start":42.15,"time_end":47.32},{"position":11,"content":"you'll find your supervisor is very approachable and won't mind explaining things or helping you out.","audio_url":"https://dailydictation.com/upload/ielts-listening/ielts-cambridge-14-test-1-section-2-2023-01-25-00-08-54/11.mp3","time_start":47.57,"time_end":55.15},{"position":12,"content":"You're here to learn so make the most of that opportunity.","audio_url":"https://dailydictation.com/upload/ielts-listening/ielts-cambridge-14-test-1-section-2-2023-01-25-00-08-54/12.mp3","time_start":55.81,"time_end":60.08},{"position":13,"content":"You'll be spending time in different departments during your first week","audio_url":"https://dailydictation.com/upload/ielts-listening/ielts-cambridge-14-test-1-section-2-2023-01-25-00-08-54/13.mp3","time_start":60.44,"time_end":65.08},{"position":14,"content":"so make an effort to talk to as many people as possible about their work -","audio_url":"https://dailydictation.com/upload/ielts-listening/ielts-cambridge-14-test-1-section-2-2023-01-25-00-08-54/14.mp3","time_start":65.15,"time_end":70.64},{"position":15,"content":"you'll make some new friends and find out lots of useful information.","audio_url":"https://dailydictation.com/upload/ielts-listening/ielts-cambridge-14-test-1-section-2-2023-01-25-00-08-54/15.mp3","time_start":70.97,"time_end":75.75},{"position":16,"content":"As well as having a supervisor, you'll each be assigned a mentor.","audio_url":"https://dailydictation.com/upload/ielts-listening/ielts-cambridge-14-test-1-section-2-2023-01-25-00-08-54/16.mp3","time_start":76.45,"time_end":81.53},{"position":17,"content":"This person will be someone who's recently completed an apprenticeship","audio_url":"https://dailydictation.com/upload/ielts-listening/ielts-cambridge-14-test-1-section-2-2023-01-25-00-08-54/17.mp3","time_start":81.96,"time_end":86.71},{"position":18,"content":"and you'll meet with them on a weekly basis.","audio_url":"https://dailydictation.com/upload/ielts-listening/ielts-cambridge-14-test-1-section-2-2023-01-25-00-08-54/18.mp3","time_start":86.84,"time_end":90.05},{"position":19,"content":"Their role is to provide help and support throughout your apprenticeship.","audio_url":"https://dailydictation.com/upload/ielts-listening/ielts-cambridge-14-test-1-section-2-2023-01-25-00-08-54/19.mp3","time_start":90.4,"time_end":95.43},{"position":20,"content":"Of course, this doesn't mean they'll actually do any of your work for you -","audio_url":"https://dailydictation.com/upload/ielts-listening/ielts-cambridge-14-test-1-section-2-2023-01-25-00-08-54/20.mp3","time_start":95.72,"time_end":100.0},{"position":21,"content":"instead they'll be asking you about what goals you've achieved so far,","audio_url":"https://dailydictation.com/upload/ielts-listening/ielts-cambridge-14-test-1-section-2-2023-01-25-00-08-54/21.mp3","time_start":100.16,"time_end":105.11},{"position":22,"content":"as well as helping you to identify any areas for improvement.","audio_url":"https://dailydictation.com/upload/ielts-listening/ielts-cambridge-14-test-1-section-2-2023-01-25-00-08-54/22.mp3","time_start":105.24,"time_end":109.88},{"position":23,"content":"You can also discuss your more long-term ambitions with them as well.","audio_url":"https://dailydictation.com/upload/ielts-listening/ielts-cambridge-14-test-1-section-2-2023-01-25-00-08-54/23.mp3","time_start":110.2,"time_end":114.65},{"position":24,"content":"Now I just want to run through a few company policies for our apprenticeship scheme with you...","audio_url":"https://dailydictation.com/upload/ielts-listening/ielts-cambridge-14-test-1-section-2-2023-01-25-00-08-54/24.mp3","time_start":115.39,"time_end":121.29},{"position":25,"content":"Most importantly, the internet.","audio_url":"https://dailydictation.com/upload/ielts-listening/ielts-cambridge-14-test-1-section-2-2023-01-25-00-08-54/25.mp3","time_start":121.64,"time_end":124.71},{"position":26,"content":"As part of your job you'll be doing some research online","audio_url":"https://dailydictation.com/upload/ielts-listening/ielts-cambridge-14-test-1-section-2-2023-01-25-00-08-54/26.mp3","time_start":125.01,"time_end":129.29},{"position":27,"content":"so obviously you'll have unlimited access for that","audio_url":"https://dailydictation.com/upload/ielts-listening/ielts-cambridge-14-test-1-section-2-2023-01-25-00-08-54/27.mp3","time_start":129.35,"time_end":133.29},{"position":28,"content":"but please don't use it for personal use,","audio_url":"https://dailydictation.com/upload/ielts-listening/ielts-cambridge-14-test-1-section-2-2023-01-25-00-08-54/28.mp3","time_start":133.39,"time_end":137.11},{"position":29,"content":"you'll have your own phones for that.","audio_url":"https://dailydictation.com/upload/ielts-listening/ielts-cambridge-14-test-1-section-2-2023-01-25-00-08-54/29.mp3","time_start":137.17,"time_end":139.73},{"position":30,"content":"Some of you have already asked me about flexible working.","audio_url":"https://dailydictation.com/upload/ielts-listening/ielts-cambridge-14-test-1-section-2-2023-01-25-00-08-54/30.mp3","time_start":140.55,"time_end":144.55},{"position":31,"content":"After your probationary three-month period,","audio_url":"https://dailydictation.com/upload/ielts-listening/ielts-cambridge-14-test-1-section-2-2023-01-25-00-08-54/31.mp3","time_start":144.92,"time_end":148.03},{"position":32,"content":"some of you will be eligible for this,","audio_url":"https://dailydictation.com/upload/ielts-listening/ielts-cambridge-14-test-1-section-2-2023-01-25-00-08-54/32.mp3","time_start":148.11,"time_end":150.45},{"position":33,"content":"but it will depend on which department you're in and what your personal circumstances are.","audio_url":"https://dailydictation.com/upload/ielts-listening/ielts-cambridge-14-test-1-section-2-2023-01-25-00-08-54/33.mp3","time_start":150.65,"time_end":157.13},{"position":34,"content":"So please don't assume you'll automatically be permitted to do this.","audio_url":"https://dailydictation.com/upload/ielts-listening/ielts-cambridge-14-test-1-section-2-2023-01-25-00-08-54/34.mp3","time_start":157.24,"time_end":162.19},{"position":35,"content":"I want to make sure there's no confusion about our holiday policy.","audio_url":"https://dailydictation.com/upload/ielts-listening/ielts-cambridge-14-test-1-section-2-2023-01-25-00-08-54/35.mp3","time_start":162.91,"time_end":167.33},{"position":36,"content":"Apart from any statutory public holidays","audio_url":"https://dailydictation.com/upload/ielts-listening/ielts-cambridge-14-test-1-section-2-2023-01-25-00-08-54/36.mp3","time_start":167.6,"time_end":170.71},{"position":37,"content":"we ask that you don't book any holidays until after your six-month apprenticeship has finished.","audio_url":"https://dailydictation.com/upload/ielts-listening/ielts-cambridge-14-test-1-section-2-2023-01-25-00-08-54/37.mp3","time_start":170.79,"time_end":177.59},{"position":38,"content":"Time off should only be taken if you are unwell.","audio_url":"https://dailydictation.com/upload/ielts-listening/ielts-cambridge-14-test-1-section-2-2023-01-25-00-08-54/38.mp3","time_start":178.03,"time_end":181.64},{"position":39,"content":"Please speak to your supervisor if this is going to be a problem.","audio_url":"https://dailydictation.com/upload/ielts-listening/ielts-cambridge-14-test-1-section-2-2023-01-25-00-08-54/39.mp3","time_start":181.93,"time_end":186.21},{"position":40,"content":"You'll be expected to work a 40-hour week","audio_url":"https://dailydictation.com/upload/ielts-listening/ielts-cambridge-14-test-1-section-2-2023-01-25-00-08-54/40.mp3","time_start":187.2,"time_end":190.23},{"position":41,"content":"but there may be opportunities to do overtime during busy periods.","audio_url":"https://dailydictation.com/upload/ielts-listening/ielts-cambridge-14-test-1-section-2-2023-01-25-00-08-54/41.mp3","time_start":190.33,"time_end":195.59},{"position":42,"content":"Although you're not required to do this,","audio_url":"https://dailydictation.com/upload/ielts-listening/ielts-cambridge-14-test-1-section-2-2023-01-25-00-08-54/42.mp3","time_start":196.12,"time_end":198.49},{"position":43,"content":"it can be a valuable experience -","audio_url":"https://dailydictation.com/upload/ielts-listening/ielts-cambridge-14-test-1-section-2-2023-01-25-00-08-54/43.mp3","time_start":198.49,"time_end":201.27},{"position":44,"content":"so we advise you to take it up if possible.","audio_url":"https://dailydictation.com/upload/ielts-listening/ielts-cambridge-14-test-1-section-2-2023-01-25-00-08-54/44.mp3","time_start":201.27,"time_end":205.01},{"position":45,"content":"Obviously, we understand that people do have commitments outside work,","audio_url":"https://dailydictation.com/upload/ielts-listening/ielts-cambridge-14-test-1-section-2-2023-01-25-00-08-54/45.mp3","time_start":205.23,"time_end":210.27},{"position":46,"content":"so don't worry if there are times when you are unavailable.","audio_url":"https://dailydictation.com/upload/ielts-listening/ielts-cambridge-14-test-1-section-2-2023-01-25-00-08-54/46.mp3","time_start":210.36,"time_end":214.12},{"position":47,"content":"As you know, we don't have a formal dress code here -","audio_url":"https://dailydictation.com/upload/ielts-listening/ielts-cambridge-14-test-1-section-2-2023-01-25-00-08-54/47.mp3","time_start":214.91,"time_end":218.85},{"position":48,"content":"you may wear casual clothes as long as they're practical -","audio_url":"https://dailydictation.com/upload/ielts-listening/ielts-cambridge-14-test-1-section-2-2023-01-25-00-08-54/48.mp3","time_start":218.96,"time_end":223.28},{"position":49,"content":"and the only restriction for shoes we have is on high heels for health and safety reasons.","audio_url":"https://dailydictation.com/upload/ielts-listening/ielts-cambridge-14-test-1-section-2-2023-01-25-00-08-54/49.mp3","time_start":223.43,"time_end":230.16},{"position":50,"content":"Comfortable shoes like trainers are preferable.","audio_url":"https://dailydictation.com/upload/ielts-listening/ielts-cambridge-14-test-1-section-2-2023-01-25-00-08-54/50.mp3","time_start":230.33,"time_end":233.57},{"position":51,"content":"There's a heavily subsidised canteen on site where you can get hot meals or salads cheaply.","audio_url":"https://dailydictation.com/upload/ielts-listening/ielts-cambridge-14-test-1-section-2-2023-01-25-00-08-54/51.mp3","time_start":234.44,"time_end":241.6},{"position":52,"content":"Snacks and drinks are also provided -","audio_url":"https://dailydictation.com/upload/ielts-listening/ielts-cambridge-14-test-1-section-2-2023-01-25-00-08-54/52.mp3","time_start":241.83,"time_end":244.52},{"position":53,"content":"so we've decided to introduce a no packed lunch policy.","audio_url":"https://dailydictation.com/upload/ielts-listening/ielts-cambridge-14-test-1-section-2-2023-01-25-00-08-54/53.mp3","time_start":244.59,"time_end":249.49},{"position":54,"content":"This is partly to encourage healthy eating at work","audio_url":"https://dailydictation.com/upload/ielts-listening/ielts-cambridge-14-test-1-section-2-2023-01-25-00-08-54/54.mp3","time_start":249.67,"time_end":253.39},{"position":55,"content":"and partly to stop people from eating at their workstation, which is unhygienic.","audio_url":"https://dailydictation.com/upload/ielts-listening/ielts-cambridge-14-test-1-section-2-2023-01-25-00-08-54/55.mp3","time_start":253.45,"time_end":259.43},{"position":56,"content":"OK moving on to...","audio_url":"https://dailydictation.com/upload/ielts-listening/ielts-cambridge-14-test-1-section-2-2023-01-25-00-08-54/56.mp3","time_start":260.07,"time_end":262.25}]}