{"id":"es-380","language":"spanish","category_slug":"spanish-intermediate","category_name":"Spanish Listening - Intermediate","position":380,"title":"380. ¿Qué deporte es popular en tu país?","subtitle":"Janina / Honduras","level":"Intermediate Spanish","parts":3,"url":"https://www.spanishlistening.org/content/380-janina-honduras-sports.html","audio_url":"","youtube_video_id":"","vimeo_video_id":"176233666","video_url":"https://player.vimeo.com/video/176233666","details_cached_at":"2026-06-29T13:55:06","challenges":[{"position":1,"content":"La pregunta es: ¿qué deporte enloquece a la gente de mi país?","audio_url":"","time_start":null,"time_end":null},{"position":2,"content":"Definitivamente el futbol. Aquí no se apoyan otros deportes, sino que solamente se enfocan en el futbol y la gente se apasiona, especialmente los hombres, cuando hay partidos de la liga nacional.","audio_url":"","time_start":null,"time_end":null},{"position":3,"content":"Entonces creo que el deporte que más disfrutan en mi país es el futbol, ya que los demás deportes pues casi no se conoce realmente cuáles son, los que tienen algún evento y, el futbol nacional en todos los canales de televisión se puede ver un partido casi los... todos los fines de semana.","audio_url":"","time_start":null,"time_end":null}]}